Metadata-Version: 2.1
Name: helloworld-eliya
Version: 0.0.1
Summary: Say Hello
Home-page: https://github.com/talisel
Author: Tal Barak
Author-email: talisel@gmail.com
License: UNKNOWN
Platform: UNKNOWN
Classifier: Programming Language :: Python :: 3
Classifier: Programming Language :: Python :: 3.6
Classifier: Programming Language :: Python :: 3.7
Classifier: License :: OSI Approved :: GNU General Public License v2 or later (GPLv2+)
Classifier: Operating System :: OS Independent
Provides-Extra: dev
License-File: LICENSE.txt
